aiologger_x9_wrapper/__init__.py
aiologger_x9_wrapper/dto.py
aiologger_x9_wrapper/enums.py
aiologger_x9_wrapper/formatters.py
aiologger_x9_wrapper/handlers.py
aiologger_x9_wrapper/logger.py
aiologger_x9_wrapper/types.py
aiologger_x9_wrapper-0.2.2.dist-info/licenses/LICENSE
aiologger_x9_wrapper-0.2.2.dist-info/METADATA
aiologger_x9_wrapper-0.2.2.dist-info/WHEEL
aiologger_x9_wrapper-0.2.2.dist-info/top_level.txt
aiologger_x9_wrapper-0.2.2.dist-info/RECORD
