Metadata-Version: 2.4
Name: aiologger_x9_wrapper
Version: 0.2.2
Summary: High-level wrapper for aiologger. Asynchronous logging with automatic log directory management and daily file rotation.
Author-email: Sam <svsposobin@gmail.com>
License-Expression: MIT
Project-URL: Homepage, https://github.com/svsposobin/aiologger_x9_wrapper
Keywords: async,logging,logger
Classifier: Programming Language :: Python :: 3
Classifier: Operating System :: OS Independent
Classifier: Topic :: System :: Logging
Requires-Python: >=3.10
License-File: LICENSE
Requires-Dist: aiofiles>=24.1.0
Requires-Dist: aiologger>=0.7.0
Dynamic: license-file
